CHANGES.txt
LICENSE.txt
MANIFEST.in
README.txt
buildout.cfg
setup.py
eggs/ZConfig-4.2-py3.10.egg/EGG-INFO/LICENSE.txt
eggs/ZConfig-4.2-py3.10.egg/EGG-INFO/entry_points.txt
eggs/ZConfig-4.2-py3.10.egg/EGG-INFO/requires.txt
eggs/ZConfig-4.2-py3.10.egg/EGG-INFO/top_level.txt
eggs/ZConfig-4.2-py3.10.egg/ZConfig/schemaless.txt
eggs/ZConfig-4.2-py3.10.egg/ZConfig/tests/input/non-ascii.txt
eggs/ZConfig-4.2-py3.10.egg/ZConfig/tests/library/README.txt
eggs/ZConfig-4.2-py3.10.egg/ZConfig/tests/zipsource/README.txt
eggs/p01.checker-0.5.16-py3.10.egg/EGG-INFO/SOURCES.txt
eggs/p01.checker-0.5.16-py3.10.egg/EGG-INFO/dependency_links.txt
eggs/p01.checker-0.5.16-py3.10.egg/EGG-INFO/namespace_packages.txt
eggs/p01.checker-0.5.16-py3.10.egg/EGG-INFO/requires.txt
eggs/p01.checker-0.5.16-py3.10.egg/EGG-INFO/top_level.txt
eggs/p01.checker-0.5.16-py3.10.egg/p01/checker/checker.txt
eggs/p01.checker-0.5.16-py3.10.egg/p01/checker/sample/tab.txt
eggs/p01.recipe.setup-0.8.19-py3.10.egg/EGG-INFO/SOURCES.txt
eggs/p01.recipe.setup-0.8.19-py3.10.egg/EGG-INFO/dependency_links.txt
eggs/p01.recipe.setup-0.8.19-py3.10.egg/EGG-INFO/entry_points.txt
eggs/p01.recipe.setup-0.8.19-py3.10.egg/EGG-INFO/namespace_packages.txt
eggs/p01.recipe.setup-0.8.19-py3.10.egg/EGG-INFO/requires.txt
eggs/p01.recipe.setup-0.8.19-py3.10.egg/EGG-INFO/top_level.txt
eggs/p01.recipe.setup-0.8.19-py3.10.egg/p01/recipe/setup/README.txt
eggs/p01.recipe.setup-0.8.19-py3.10.egg/p01/recipe/setup/checker.txt
eggs/p01.recipe.setup-0.8.19-py3.10.egg/p01/recipe/setup/cmd.txt
eggs/p01.recipe.setup-0.8.19-py3.10.egg/p01/recipe/setup/copy.txt
eggs/p01.recipe.setup-0.8.19-py3.10.egg/p01/recipe/setup/download.txt
eggs/p01.recipe.setup-0.8.19-py3.10.egg/p01/recipe/setup/fetch.txt
eggs/p01.recipe.setup-0.8.19-py3.10.egg/p01/recipe/setup/i18n.txt
eggs/p01.recipe.setup-0.8.19-py3.10.egg/p01/recipe/setup/importchecker.txt
eggs/p01.recipe.setup-0.8.19-py3.10.egg/p01/recipe/setup/index.txt
eggs/p01.recipe.setup-0.8.19-py3.10.egg/p01/recipe/setup/mkdir.txt
eggs/p01.recipe.setup-0.8.19-py3.10.egg/p01/recipe/setup/mkfile.txt
eggs/p01.recipe.setup-0.8.19-py3.10.egg/p01/recipe/setup/paste.txt
eggs/p01.recipe.setup-0.8.19-py3.10.egg/p01/recipe/setup/script.txt
eggs/p01.recipe.setup-0.8.19-py3.10.egg/p01/recipe/setup/scripts.txt
eggs/p01.recipe.setup-0.8.19-py3.10.egg/p01/recipe/setup/supervisor.txt
eggs/p01.recipe.setup-0.8.19-py3.10.egg/p01/recipe/setup/template.txt
eggs/p01.recipe.setup-0.8.19-py3.10.egg/p01/recipe/setup/winservice.txt
eggs/six-1.17.0-py3.10.egg/EGG-INFO/top_level.txt
eggs/zc.recipe.egg-2.0.7-py3.10.egg/EGG-INFO/SOURCES.txt
eggs/zc.recipe.egg-2.0.7-py3.10.egg/EGG-INFO/dependency_links.txt
eggs/zc.recipe.egg-2.0.7-py3.10.egg/EGG-INFO/entry_points.txt
eggs/zc.recipe.egg-2.0.7-py3.10.egg/EGG-INFO/namespace_packages.txt
eggs/zc.recipe.egg-2.0.7-py3.10.egg/EGG-INFO/requires.txt
eggs/zc.recipe.egg-2.0.7-py3.10.egg/EGG-INFO/top_level.txt
eggs/zc.recipe.testrunner-3.2-py3.10.egg/EGG-INFO/LICENSE.txt
eggs/zc.recipe.testrunner-3.2-py3.10.egg/EGG-INFO/entry_points.txt
eggs/zc.recipe.testrunner-3.2-py3.10.egg/EGG-INFO/namespace_packages.txt
eggs/zc.recipe.testrunner-3.2-py3.10.egg/EGG-INFO/requires.txt
eggs/zc.recipe.testrunner-3.2-py3.10.egg/EGG-INFO/top_level.txt
eggs/zope.exceptions-5.2-py3.10.egg/EGG-INFO/LICENSE.txt
eggs/zope.exceptions-5.2-py3.10.egg/EGG-INFO/namespace_packages.txt
eggs/zope.exceptions-5.2-py3.10.egg/EGG-INFO/requires.txt
eggs/zope.exceptions-5.2-py3.10.egg/EGG-INFO/top_level.txt
eggs/zope.interface-7.2-py3.10-win-amd64.egg/EGG-INFO/LICENSE.txt
eggs/zope.interface-7.2-py3.10-win-amd64.egg/EGG-INFO/namespace_packages.txt
eggs/zope.interface-7.2-py3.10-win-amd64.egg/EGG-INFO/requires.txt
eggs/zope.interface-7.2-py3.10-win-amd64.egg/EGG-INFO/top_level.txt
eggs/zope.testing-5.1-py3.10.egg/EGG-INFO/LICENSE.txt
eggs/zope.testing-5.1-py3.10.egg/EGG-INFO/namespace_packages.txt
eggs/zope.testing-5.1-py3.10.egg/EGG-INFO/requires.txt
eggs/zope.testing-5.1-py3.10.egg/EGG-INFO/top_level.txt
eggs/zope.testing-5.1-py3.10.egg/zope/testing/cleanup.txt
eggs/zope.testing-5.1-py3.10.egg/zope/testing/doctestcase.txt
eggs/zope.testing-5.1-py3.10.egg/zope/testing/formparser.txt
eggs/zope.testing-5.1-py3.10.egg/zope/testing/loggingsupport.txt
eggs/zope.testing-5.1-py3.10.egg/zope/testing/module.txt
eggs/zope.testing-5.1-py3.10.egg/zope/testing/renormalizing.txt
eggs/zope.testrunner-7.4-py3.10.egg/EGG-INFO/entry_points.txt
eggs/zope.testrunner-7.4-py3.10.egg/EGG-INFO/namespace_packages.txt
eggs/zope.testrunner-7.4-py3.10.egg/EGG-INFO/requires.txt
eggs/zope.testrunner-7.4-py3.10.egg/EGG-INFO/top_level.txt
src/m01.fs.egg-info/PKG-INFO
src/m01.fs.egg-info/SOURCES.txt
src/m01.fs.egg-info/dependency_links.txt
src/m01.fs.egg-info/namespace_packages.txt
src/m01.fs.egg-info/not-zip-safe
src/m01.fs.egg-info/requires.txt
src/m01.fs.egg-info/top_level.txt
